cdlake-0.1.4.dist-info/METADATA
cdlake-0.1.4.dist-info/WHEEL
cdlake-0.1.4.dist-info/licenses/LICENSE
cdlake/_internal.pyi
cdlake/py.typed
cdlake/filesystem.py
cdlake/lake.py
cdlake/__init__.py
cdlake/_internal.abi3.so
cdlake-0.1.4.dist-info/RECORD
